README.md
setup.cfg
setup.py
QMUtilities.egg-info/PKG-INFO
QMUtilities.egg-info/SOURCES.txt
QMUtilities.egg-info/dependency_links.txt
QMUtilities.egg-info/requires.txt
QMUtilities.egg-info/top_level.txt
security/__init__.py
security/secret_manager.py
security/validate.py